xanathar/__init__.py
xanathar/codegen.py
xanathar/compiler.py
xanathar/interpreter.py
xanathar/logs.py
xanathar/strings.py
xanathar/xast.py
xanathar-1.0.1.data/data/grammar/GRAMMAR.ebnf
xanathar-1.0.1.data/data/stdlib/stdio.so
xanathar-1.0.1.data/data/stdlib/stdlib.so
xanathar-1.0.1.dist-info/METADATA
xanathar-1.0.1.dist-info/WHEEL
xanathar-1.0.1.dist-info/top_level.txt
xanathar-1.0.1.dist-info/RECORD
