Metadata-Version: 2.1
Name: xanathar
Version: 1.0.1
Summary: The Xanathar programming Language
Home-page: https://bitbucket.org/xanathardevs/xanathar/src/master/
Author: Max Steinberg
Author-email: maxssteinberg@gmail.com
License: UNKNOWN
Platform: UNKNOWN
Classifier: Programming Language :: Python :: 3
Classifier: License :: OSI Approved :: MIT License
Classifier: Operating System :: OS Independent
Requires-Dist: lark-parser
Requires-Dist: llvmlite
